[
  {
    "question": "पहला आईफोन (iPhone) कब लॉन्च हुआ था?",
    "options": {
      "a": "2007",
      "b": "2008",
      "c": "2009",
      "d": "2010"
    },
    "answer": "a",
    "explanation": "स्टीव जॉब्स ने 9 जनवरी 2007 को पहले आईफोन का अनावरण किया और यह उसी साल 29 जून को अमेरिका में जारी किया गया।",
    "difficulty": "easy"
  },
  {
    "question": "आईफोन किस ऑपरेटिंग सिस्टम पर काम करता है?",
    "options": {
      "a": "आई.ओ.एस (iOS)",
      "b": "एंड्रॉइड (Android)",
      "c": "विंडोज (Windows)",
      "d": "लाइनक्स (Linux)"
    },
    "answer": "a",
    "explanation": "आईफोन के ऑपरेटिंग सिस्टम को आईओएस (iOS) कहा जाता है, जिसका मूल नाम आईफोन ओएस (iPhone OS) था।",
    "difficulty": "easy"
  },
  {
    "question": "आईफोन में 'सिरी' (Siri) नामक वर्चुअल असिस्टेंट कब पेश किया गया था?",
    "options": {
      "a": "2011",
      "b": "2010",
      "c": "2012",
      "d": "2013"
    },
    "answer": "a",
    "explanation": "सिरी को पहली बार आईफोन 4एस (iPhone 4S) के साथ 2011 में पेश किया गया था।",
    "difficulty": "medium"
  },
  {
    "question": "आईफोन के किस मॉडल में पहली बार 'रेटिना डिस्प्ले' (Retina Display) का इस्तेमाल किया गया था?",
    "options": {
      "a": "आईफोन 4 (iPhone 4)",
      "b": "आईफोन 3जी (iPhone 3G)",
      "c": "आईफोन 5 (iPhone 5)",
      "d": "आईफोन 6 (iPhone 6)"
    },
    "answer": "a",
    "explanation": "रेटिना डिस्प्ले को आईफोन 4 में पेश किया गया था, जिसमें मानक से अधिक पिक्सेल घनत्व था।",
    "difficulty": "medium"
  },
  {
    "question": "आईफोन के किस मॉडल में 'फेस आईडी' (Face ID) को पहली बार पेश किया गया था?",
    "options": {
      "a": "आईफोन एक्स (iPhone X)",
      "b": "आईफोन 8 (iPhone 8)",
      "c": "आईफोन 7 (iPhone 7)",
      "d": "आईफोन 6एस (iPhone 6S)"
    },
    "answer": "a",
    "explanation": "फेस आईडी (चेहरे की पहचान) को पहली बार 2017 में आईफोन एक्स (iPhone X) के साथ पेश किया गया था।",
    "difficulty": "easy"
  },
  {
    "question": "आईफोन से 3.5 मिमी हेडफोन जैक किस मॉडल में हटाया गया था?",
    "options": {
      "a": "आईफोन 7 (iPhone 7)",
      "b": "आईफोन 6एस (iPhone 6S)",
      "c": "आईफोन 8 (iPhone 8)",
      "d": "आईफोन एक्स (iPhone X)"
    },
    "answer": "a",
    "explanation": "एप्पल ने आईफोन 7 और आईफोन 7 प्लस से 3.5 मिमी हेडफोन जैक को हटा दिया था।",
    "difficulty": "medium"
  },
  {
    "question": "किस वर्ष आईफोन ने लाइटनिंग कनेक्टर से यूएसबी-सी (USB-C) कनेक्टर में बदलाव किया?",
    "options": {
      "a": "2023",
      "b": "2022",
      "c": "2021",
      "d": "2024"
    },
    "answer": "a",
    "explanation": "एप्पल ने आईफोन 15 सीरीज के साथ लाइटनिंग पोर्ट को हटाकर यूएसबी-सी पोर्ट अपनाया।",
    "difficulty": "medium"
  },
  {
    "question": "आईफोन की किस सीरीज में पहली बार प्रो (Pro) मॉडल पेश किए गए थे?",
    "options": {
      "a": "आईफोन 11 (iPhone 11)",
      "b": "आईफोन 10 (iPhone X)",
      "c": "आईफोन 12 (iPhone 12)",
      "d": "आईफोन 13 (iPhone 13)"
    },
    "answer": "a",
    "explanation": "एप्पल ने 2019 में आईफोन 11 प्रो और 11 प्रो मैक्स के साथ 'प्रो' मॉडल पेश किए थे।",
    "difficulty": "medium"
  },
  {
    "question": "आईफोन के किस मॉडल में पहली बार 'ए-सीरीज बायोनिक चिप' (A-series Bionic chip) पेश की गई थी?",
    "options": {
      "a": "आईफोन 8 (iPhone 8)",
      "b": "आईफोन एक्स (iPhone X)",
      "c": "आईफोन 7 (iPhone 7)",
      "d": "आईफोन 6 (iPhone 6)"
    },
    "answer": "a",
    "explanation": "ए11 बायोनिक चिप को आईफोन 8, 8 प्लस और आईफोन एक्स में पहली बार पेश किया गया था।",
    "difficulty": "hard"
  },
  {
    "question": "आईफोन में 'डार्क मोड' (Dark Mode) की सुविधा किस आईओएस संस्करण में आई थी?",
    "options": {
      "a": "आई.ओ.एस 13 (iOS 13)",
      "b": "आई.ओ.एस 12 (iOS 12)",
      "c": "आई.ओ.एस 14 (iOS 14)",
      "d": "आई.ओ.एस 15 (iOS 15)"
    },
    "answer": "a",
    "explanation": "डार्क मोड, जो पूरे सिस्टम पर लागू होता है, को आईओएस 13 में पेश किया गया था।",
    "difficulty": "medium"
  },
  {
    "question": "एप्पल का पहला आईफोन किस कंपनी के साथ विशेष रूप से बेचा गया था?",
    "options": {
      "a": "एटी एंड टी (AT&T)",
      "b": "वेराइजन (Verizon)",
      "c": "टी-मोबाइल (T-Mobile)",
      "d": "स्प्रिंट (Sprint)"
    },
    "answer": "a",
    "explanation": "पहला आईफोन अमेरिका में एटी एंड टी के साथ एक विशेष अनुबंध के तहत उपलब्ध था।",
    "difficulty": "hard"
  },
  {
    "question": "आईफोन के किस मॉडल में 'डायनामिक आइलैंड' (Dynamic Island) को पहली बार पेश किया गया?",
    "options": {
      "a": "आईफोन 14 प्रो (iPhone 14 Pro)",
      "b": "आईफोन 13 प्रो (iPhone 13 Pro)",
      "c": "आईफोन 15 (iPhone 15)",
      "d": "आईफोन 14 (iPhone 14)"
    },
    "answer": "a",
    "explanation": "डायनामिक आइलैंड को पहली बार आईफोन 14 प्रो और प्रो मैक्स मॉडल में पेश किया गया था।",
    "difficulty": "hard"
  },
  {
    "question": "एप्पल का कौन सा डिवाइस आईफोन के आधार पर विकसित किया गया था?",
    "options": {
      "a": "आईपॉड टच (iPod Touch)",
      "b": "आईपैड (iPad)",
      "c": "मैकबुक (MacBook)",
      "d": "एप्पल टीवी (Apple TV)"
    },
    "answer": "a",
    "explanation": "आईपॉड टच को आईफोन के समान डिज़ाइन और ऑपरेटिंग सिस्टम के साथ बनाया गया था, लेकिन इसमें सेलुलर क्षमता नहीं थी।",
    "difficulty": "medium"
  },
  {
    "question": "आईफोन का निर्माण करने वाली मुख्य कंपनी कौन है?",
    "options": {
      "a": "फॉक्सकॉन (Foxconn)",
      "b": "सैमसंग (Samsung)",
      "c": "एप्पल (Apple)",
      "d": "मोटोरोला (Motorola)"
    },
    "answer": "a",
    "explanation": "फॉक्सकॉन एप्पल के लिए मुख्य आईफोन असेंबली पार्टनर है।",
    "difficulty": "medium"
  },
  {
    "question": "आईफोन के किस मॉडल में 'टच आईडी' (Touch ID) को पहली बार पेश किया गया था?",
    "options": {
      "a": "आईफोन 5एस (iPhone 5S)",
      "b": "आईफोन 5 (iPhone 5)",
      "c": "आईफोन 6 (iPhone 6)",
      "d": "आईफोन 4एस (iPhone 4S)"
    },
    "answer": "a",
    "explanation": "टच आईडी (फिंगरप्रिंट सेंसर) को पहली बार आईफोन 5एस के होम बटन में एकीकृत किया गया था।",
    "difficulty": "medium"
  },
  {
    "question": "आईफोन में 'फोटोग्राफिक स्टाइल्स' (Photographic Styles) नामक सुविधा किस मॉडल में जोड़ी गई थी?",
    "options": {
      "a": "आईफोन 13 (iPhone 13)",
      "b": "आईफोन 12 (iPhone 12)",
      "c": "आईफोन 11 (iPhone 11)",
      "d": "आईफोन 14 (iPhone 14)"
    },
    "answer": "a",
    "explanation": "फोटोग्राफिक स्टाइल्स की सुविधा आईफोन 13 सीरीज के साथ आई, जो तस्वीरों को कैप्चर करने से पहले अनुकूलित करती है।",
    "difficulty": "hard"
  },
  {
    "question": "आईफोन 6 (iPhone 6) में कौन सा नया डिज़ाइन पेश किया गया था?",
    "options": {
      "a": "बड़ा, गोलाकार किनारे वाला डिज़ाइन",
      "b": "फ्लैट किनारे वाला डिज़ाइन",
      "c": "छोटा, गोल डिज़ाइन",
      "d": "प्लास्टिक बॉडी"
    },
    "answer": "a",
    "explanation": "आईफोन 6 और 6 प्लस में बड़ा, पतला और गोलाकार किनारे वाला डिज़ाइन पेश किया गया था।",
    "difficulty": "easy"
  },
  {
    "question": "आईफोन 12 (iPhone 12) के साथ कौन सा नया वायरलेस चार्जिंग सिस्टम पेश किया गया था?",
    "options": {
      "a": "मैगसेफ (MagSafe)",
      "b": "क्यूई (Qi)",
      "c": "पावरशेयर (Powershare)",
      "d": "एयरपावर (AirPower)"
    },
    "answer": "a",
    "explanation": "आईफोन 12 में मैगसेफ पेश किया गया था, जो चार्जिंग और एक्सेसरीज़ के लिए चुम्बकीय रूप से जुड़ता है।",
    "difficulty": "medium"
  },
  {
    "question": "आईफोन के किस मॉडल में 'ए14 बायोनिक चिप' (A14 Bionic chip) का उपयोग किया गया था?",
    "options": {
      "a": "आईफोन 12 (iPhone 12)",
      "b": "आईफोन 11 (iPhone 11)",
      "c": "आईफोन 13 (iPhone 13)",
      "d": "आईफोन 14 (iPhone 14)"
    },
    "answer": "a",
    "explanation": "ए14 बायोनिक चिप को आईफोन 12 सीरीज और आईपैड एयर (चौथी पीढ़ी) में पेश किया गया था।",
    "difficulty": "medium"
  },
  {
    "question": "आईफोन 11 (iPhone 11) में पीछे की तरफ कितने कैमरे थे?",
    "options": {
      "a": "दो",
      "b": "एक",
      "c": "तीन",
      "d": "चार"
    },
    "answer": "a",
    "explanation": "आईफोन 11 में पीछे की तरफ एक वाइड और एक अल्ट्रा-वाइड लेंस के साथ दो कैमरे थे।",
    "difficulty": "easy"
  },
  {
    "question": "आईफोन के किस संस्करण में पहला 5जी (5G) कनेक्टिविटी वाला मॉडल पेश किया गया था?",
    "options": {
      "a": "आईफोन 12",
      "b": "आईफोन 11",
      "c": "आईफोन 13",
      "d": "आईफोन एक्सएस"
    },
    "answer": "a",
    "explanation": "आईफोन 12 सीरीज एप्पल का पहला फोन था जो 5जी कनेक्टिविटी के साथ आया।",
    "difficulty": "medium"
  },
  {
    "question": "आईफोन 13 (iPhone 13) की प्रमुख विशेषता क्या थी?",
    "options": {
      "a": "बड़ा बैटरी जीवन और बेहतर कैमरा",
      "b": "यूएसबी-सी पोर्ट",
      "c": "डायनामिक आइलैंड",
      "d": "प्रोमोशन डिस्प्ले"
    },
    "answer": "a",
    "explanation": "आईफोन 13 में आईफोन 12 की तुलना में काफी बेहतर बैटरी जीवन और कैमरा प्रदर्शन था।",
    "difficulty": "medium"
  },
  {
    "question": "एप्पल आईफोन 15 सीरीज में कौन सा प्रोसेसर पेश किया गया था?",
    "options": {
      "a": "ए17 प्रो (A17 Pro)",
      "b": "ए16 बायोनिक (A16 Bionic)",
      "c": "ए15 बायोनिक (A15 Bionic)",
      "d": "ए18 बायोनिक (A18 Bionic)"
    },
    "answer": "a",
    "explanation": "आईफोन 15 प्रो और प्रो मैक्स मॉडल में ए17 प्रो चिपसेट का उपयोग किया गया था, जो 3nm तकनीक पर आधारित है।",
    "difficulty": "hard"
  },
  {
    "question": "एप्पल के 'रेटिना डिस्प्ले' का मुख्य लाभ क्या है?",
    "options": {
      "a": "उच्च पिक्सेल घनत्व और तीक्ष्ण दृश्य",
      "b": "बेहतर ध्वनि की गुणवत्ता",
      "c": "तेज चार्जिंग",
      "d": "फोन का वजन कम करना"
    },
    "answer": "a",
    "explanation": "रेटिना डिस्प्ले में पिक्सेल इतने घने होते हैं कि इंसान की आंखें व्यक्तिगत पिक्सेल को अलग नहीं कर सकती हैं, जिससे दृश्य तीक्ष्ण दिखाई देते हैं।",
    "difficulty": "easy"
  },
  {
    "question": "आईफोन के किस मॉडल में पहली बार 'ए-सीरीज' प्रोसेसर को 'बायोनिक' नाम दिया गया था?",
    "options": {
      "a": "आईफोन 8",
      "b": "आईफोन 7",
      "c": "आईफोन एक्स",
      "d": "आईफोन 6एस"
    },
    "answer": "a",
    "explanation": "ए11 बायोनिक चिप आईफोन 8 के साथ पेश की गई थी, जिसने 'बायोनिक' नाम की शुरुआत की।",
    "difficulty": "hard"
  }
]

